pth.py
pth-0.3.0.dist-info/RECORD
pth-0.3.0.dist-info/top_level.txt
pth-0.3.0.dist-info/DESCRIPTION.rst
pth-0.3.0.dist-info/METADATA
pth-0.3.0.dist-info/metadata.json
pth-0.3.0.dist-info/WHEEL
